ezfit/__init__.py
ezfit/constraints.py
ezfit/examples.py
ezfit/exceptions.py
ezfit/fit.py
ezfit/functions.py
ezfit/mcmc_diagnostics.py
ezfit/model.py
ezfit/optimizers.py
ezfit/statistics.py
ezfit/types.py
ezfit/visualization.py
ezfit-0.5.7.dist-info/METADATA
ezfit-0.5.7.dist-info/WHEEL
ezfit-0.5.7.dist-info/RECORD
