Metadata-Version: 2.4
Name: ezfit
Version: 0.5.7
Summary: Fitting in python made easy
Author-email: Harlan D Heilman <harlan.heilman@wsu.edu>
License-Expression: GPL-2.0
Requires-Python: >=3.13
Requires-Dist: arviz>=0.18.0
Requires-Dist: corner
Requires-Dist: emcee>=3.1.0
Requires-Dist: matplotlib>=3.10.0
Requires-Dist: numba>=0.63.1
Requires-Dist: numpy>=1.26.4
Requires-Dist: pandas>=2.2.2
Requires-Dist: scikit-learn>=1.8.0
Requires-Dist: scipy>=1.16.3
Requires-Dist: tqdm>=4.67.1
Provides-Extra: all
Requires-Dist: ipykernel>=6.25.0; extra == 'all'
Requires-Dist: jupyter>=1.0.0; extra == 'all'
Provides-Extra: dev
Requires-Dist: mypy; extra == 'dev'
Requires-Dist: ruff>=0.14.8; extra == 'dev'
Requires-Dist: scipy-stubs; extra == 'dev'
Provides-Extra: docs
Requires-Dist: furo>=2023.9.10; extra == 'docs'
Requires-Dist: ipykernel>=6.25.0; extra == 'docs'
Requires-Dist: jupyter>=1.0.0; extra == 'docs'
Requires-Dist: myst-nb>=1.0.0; extra == 'docs'
Requires-Dist: sphinx-autodoc-typehints>=1.24.0; extra == 'docs'
Requires-Dist: sphinx-copybutton>=0.5.0; extra == 'docs'
Requires-Dist: sphinx-design>=0.5.0; extra == 'docs'
Requires-Dist: sphinx>=7.0.0; extra == 'docs'
Provides-Extra: notebook
Requires-Dist: ipykernel>=6.25.0; extra == 'notebook'
Requires-Dist: jupyter>=1.0.0; extra == 'notebook'
